{
    "reference": {
        "@otherprops": "legaltopicdossiertips",
        "@audience": "res;lps",
        "@id": "legaltopicdossiertips",
        "title": "Topic Summaries List",
        "prolog": {
            "author": "Barb Bruns",
            "copyright": {
                "copyryear": {
                    "@year": "2009"
                },
                "copyrholder": "Lexisnexis"
            },
            "critdates": {
                "created": {
                    "@date": "2007-07-05"
                }
            },
            "metadata": {
                "prodinfo": {
                    "prodname": "Lexis Advance",
                    "vrmlist": {
                        "vrm": {
                            "@version": "1"
                        }
                    }
                }
            }
        },
        "refbody": {
            "section": [
                {
                    "p": [
                        {
                            "uicontrol": [
                                {
                                    "#tail": "from",
                                    "#text": "View reports"
                                },
                                {
                                    "#tail": ", or select the icon",
                                    "#text": "About This Document"
                                }
                            ],
                            "image": {
                                "@alt": "Topic Summaries report",
                                "@href": "dossier-logo.png",
                                "@placement": "inline",
                                "#tail": "in the"
                            },
                            "ph": {
                                "@keyref": "companyfirst",
                                "#tail": "Headnotes of a case, the list of topic summary reports for that legal topic is displayed."
                            },
                            "#text": "When you select"
                        },
                        "From this page, you can select a single report, or select a delivery option described below."
                    ]
                },
                {
                    "p": [
                        null,
                        "A topic summary contains these items:",
                        null
                    ]
                }
            ],
            "properties": [
                {
                    "prophead": {
                        "propvaluehd": "Item",
                        "propdeschd": "Description"
                    },
                    "property": [
                        {
                            "propvalue": {
                                "image": {
                                    "@alt": "Save",
                                    "@href": "Download.png",
                                    "@placement": "inline"
                                }
                            },
                            "propdesc": {
                                "uicontrol": {
                                    "#tail": "icon at the top of the column. (Delivery options are consolidated under the icon for the last delivery option you used.)",
                                    "#text": "Download"
                                },
                                "#text": "To select one or more documents to save to your computer, select the checkboxes next to the documents in the list, and then select the"
                            }
                        },
                        {
                            "propvalue": {
                                "image": {
                                    "@alt": "Email",
                                    "@href": "Email.png",
                                    "@placement": "inline"
                                }
                            },
                            "propdesc": {
                                "uicontrol": {
                                    "#tail": "icon at the top of the column.",
                                    "#text": "Email"
                                },
                                "#text": "To select one or more documents to email, select the checkboxes next to the documents in the list, and then select the"
                            }
                        },
                        {
                            "propvalue": {
                                "image": {
                                    "@alt": "Print to attached printer",
                                    "@href": "print.png",
                                    "@placement": "inline"
                                }
                            },
                            "propdesc": {
                                "uicontrol": {
                                    "#tail": "icon at the top of the column.",
                                    "#text": "Print"
                                },
                                "#text": "To select one or more documents to open as a PDF document you can save or print to an attached printer, select the checkboxes next to the documents in the list, and then select the"
                            }
                        },
                        {
                            "propvalue": {
                                "image": {
                                    "@alt": "Printable Page",
                                    "@href": "Printablepage.png",
                                    "@placement": "inline",
                                    "#tail": "Printable page"
                                }
                            },
                            "propdesc": "Click to view the list in a printer-friendly format."
                        }
                    ]
                },
                {
                    "prophead": {
                        "propvaluehd": "Item",
                        "propdeschd": "Description"
                    },
                    "property": [
                        {
                            "propvalue": "Topic index",
                            "propdesc": "Select this to see the topic's placement in the legal topic hierarchy."
                        },
                        {
                            "propvalue": "View all documents for this topic",
                            "propdesc": "Select this to see a results list of all the documents that address this topic."
                        },
                        {
                            "propvalue": "Summary",
                            "propdesc": "A definition and summary of the legal topic of the report."
                        },
                        {
                            "propvalue": "Seminal Cases",
                            "propdesc": {
                                "ph": {
                                    "@keyref": "shepsignalsingularfirst",
                                    "#tail": "for each for each, and a link to the full text of the case."
                                },
                                "#text": "A list of seminal cases for the legal topic, with the"
                            }
                        },
                        {
                            "propvalue": "Topic Summary Hierarchy",
                            "propdesc": "The topic's placement in the legal topic hierarchy."
                        }
                    ]
                }
            ]
        }
    }
}